[
  {
    "job_name": "lint",
    "job_id": 40566687358,
    "steps": [
      {
        "name": "Set up job",
        "conclusion": "success",
        "number": 1,
        "status": "completed"
      },
      {
        "name": "Set up runner",
        "conclusion": "success",
        "number": 2,
        "status": "completed"
      },
      {
        "name": "Run actions/checkout@v4",
        "conclusion": "success",
        "number": 3,
        "status": "completed"
      },
      {
        "name": "compute metadata",
        "conclusion": "success",
        "number": 4,
        "status": "completed"
      },
      {
        "name": "Run git fetch --depth 1 origin cd6f4f263bd42688096064825dfa668bde2d3720",
        "conclusion": "success",
        "number": 5,
        "status": "completed"
      },
      {
        "name": "Run ./build/github/get-engflow-keys.sh",
        "conclusion": "success",
        "number": 6,
        "status": "completed"
      },
      {
        "name": "Run ./build/github/prepare-summarize-build.sh",
        "conclusion": "success",
        "number": 7,
        "status": "completed"
      },
      {
        "name": "run lint tests",
        "conclusion": "failure",
        "number": 8,
        "status": "completed"
      },
      {
        "name": "upload build results",
        "conclusion": "success",
        "number": 9,
        "status": "completed"
      },
      {
        "name": "clean up",
        "conclusion": "success",
        "number": 10,
        "status": "completed"
      },
      {
        "name": "Post Run actions/checkout@v4",
        "conclusion": "success",
        "number": 19,
        "status": "completed"
      },
      {
        "name": "Complete runner",
        "conclusion": "success",
        "number": 20,
        "status": "completed"
      },
      {
        "name": "Complete job",
        "conclusion": "success",
        "number": 21,
        "status": "completed"
      }
    ]
  },
  {
    "job_name": "unit_tests",
    "job_id": 40566689973,
    "steps": [
      {
        "name": "Set up job",
        "conclusion": "success",
        "number": 1,
        "status": "completed"
      },
      {
        "name": "Set up runner",
        "conclusion": "success",
        "number": 2,
        "status": "completed"
      },
      {
        "name": "Run actions/checkout@v4",
        "conclusion": "success",
        "number": 3,
        "status": "completed"
      },
      {
        "name": "compute metadata",
        "conclusion": "success",
        "number": 4,
        "status": "completed"
      },
      {
        "name": "Run ./build/github/get-engflow-keys.sh",
        "conclusion": "success",
        "number": 5,
        "status": "completed"
      },
      {
        "name": "Run ./build/github/prepare-summarize-build.sh",
        "conclusion": "success",
        "number": 6,
        "status": "completed"
      },
      {
        "name": "run tests",
        "conclusion": "failure",
        "number": 7,
        "status": "completed"
      },
      {
        "name": "upload test results",
        "conclusion": "success",
        "number": 8,
        "status": "completed"
      },
      {
        "name": "clean up",
        "conclusion": "success",
        "number": 9,
        "status": "completed"
      },
      {
        "name": "Post Run actions/checkout@v4",
        "conclusion": "success",
        "number": 17,
        "status": "completed"
      },
      {
        "name": "Complete runner",
        "conclusion": "success",
        "number": 18,
        "status": "completed"
      },
      {
        "name": "Complete job",
        "conclusion": "success",
        "number": 19,
        "status": "completed"
      }
    ]
  }
]